EBglmnet.cpython-310-darwin.so
EBglmnet/CVonePair.py
EBglmnet/EBelasticNet.py
EBglmnet/EBglmnet.cpython-310-darwin.so
EBglmnet/EBlassoNEG.py
EBglmnet/EmpBayesGlmnet.py
EBglmnet/__init__.py
EBglmnet/cvEBelasticNet.py
EBglmnet/cvEBglmnet.py
EBglmnet/cvEBlassoNE.py
EBglmnet/cvEBlassoNEG.py
EBglmnet/lambdaMax.py
EBglmnet/loadEBglmnetLib.py
EBglmnet/src/Binary.c
EBglmnet/src/Binary.h
EBglmnet/src/CVonePara.c
EBglmnet/src/Linear.c
EBglmnet/src/Linear.h
EBglmnet/src/NEG.c
EBglmnet/src/NEG.h
EBglmnet/src/elasticNet.c
EBglmnet/src/elasticNet.h
EBglmnet/src/elasticNetBinary.c
EBglmnet/src/elasticNetLinear.c
EBglmnet/src/fEBBinaryNEG.c
EBglmnet/src/fEBLinearNEG.c
EBglmnet-1.1.dist-info/METADATA
EBglmnet-1.1.dist-info/WHEEL
EBglmnet-1.1.dist-info/top_level.txt
EBglmnet-1.1.dist-info/RECORD
